lineplot/__init__.py
lineplot-0.2.2.dist-info/licenses/LICENSE
lineplot-0.2.2.dist-info/METADATA
lineplot-0.2.2.dist-info/WHEEL
lineplot-0.2.2.dist-info/top_level.txt
lineplot-0.2.2.dist-info/RECORD
