Metadata-Version: 2.4
Name: lineplot
Version: 0.2.2
Summary: A minimalist line plotting package for live updates from jupyter notebooks.
Author-email: Benoit Favre <benoit.favre@gmail.com>
License-Expression: MIT
Project-URL: Homepage, https://github.com/benob/lineplot
Project-URL: Issues, https://github.com/benob/lineplot/issues
Requires-Python: >=3.6
License-File: LICENSE
Requires-Dist: IPython
Dynamic: license-file
